cxgen/GUI.py
cxgen/__init__.py
cxgen/utils.py
cxgen/Legacy/__init__.py
cxgen/Legacy/appfile.py
cxgen/Legacy/utils.py
cxgen/Legacy/files/LICENSE-for-function.txt
cxgen/Legacy/files/manual.txt
cxgen-3.0.0.dist-info/METADATA
cxgen-3.0.0.dist-info/WHEEL
cxgen-3.0.0.dist-info/top_level.txt
cxgen-3.0.0.dist-info/RECORD
