Metadata-Version: 2.1
Name: cxgen
Version: 3.0.0
Summary: A package to generate cx_Freeze setup.py file!
Home-page: https://github.com/armaan115/cxgen
Author: Armaan Aggarwal
License: MIT
Platform: UNKNOWN
Classifier: Programming Language :: Python :: 3
Classifier: License :: OSI Approved :: MIT License
Classifier: Operating System :: OS Independent
Requires-Python: >=3, <4
